{"name": "Composite - hv - venthyr", "data": {"M4_V0_H6_C0": {"DPS": 11220}, "M3_V0_H7_C0": {"DPS": 11216}, "M5_V0_H5_C0": {"DPS": 11188}, "M2_V0_H8_C0": {"DPS": 11179}, "M3_V0_H6_C1": {"DPS": 11172}, "M2_V0_H7_C1": {"DPS": 11160}, "M3_V1_H6_C0": {"DPS": 11153}, "M4_V0_H5_C1": {"DPS": 11152}, "M2_V1_H7_C0": {"DPS": 11139}, "M4_V1_H5_C0": {"DPS": 11138}, "M6_V0_H4_C0": {"DPS": 11115}, "M1_V0_H8_C1": {"DPS": 11114}, "M1_V0_H9_C0": {"DPS": 11112}, "M2_V0_H6_C2": {"DPS": 11110}, "M2_V1_H6_C1": {"DPS": 11102}, "M3_V0_H5_C2": {"DPS": 11095}, "M3_V1_H5_C1": {"DPS": 11093}, "M1_V1_H8_C0": {"DPS": 11092}, "M5_V0_H4_C1": {"DPS": 11091}, "M1_V0_H7_C2": {"DPS": 11086}, "M0_V0_H10_C0": {"DPS": 11077}, "M5_V1_H4_C0": {"DPS": 11076}, "M2_V2_H6_C0": {"DPS": 11075}, "M1_V1_H7_C1": {"DPS": 11071}, "M3_V2_H5_C0": {"DPS": 11069}, "M4_V0_H4_C2": {"DPS": 11052}, "M1_V2_H7_C0": {"DPS": 11050}, "M4_V1_H4_C1": {"DPS": 11038}, "M0_V0_H9_C1": {"DPS": 11037}, "M2_V0_H5_C3": {"DPS": 11035}, "M1_V0_H6_C3": {"DPS": 11032}, "M2_V1_H5_C2": {"DPS": 11030}, "M0_V0_H8_C2": {"DPS": 11029}, "M7_V0_H3_C0": {"DPS": 11025}, "M1_V1_H6_C2": {"DPS": 11024}, "M4_V2_H4_C0": {"DPS": 11021}, "M0_V1_H9_C0": {"DPS": 11019}, "M2_V2_H5_C1": {"DPS": 11013}, "M0_V1_H8_C1": {"DPS": 11011}, "M1_V2_H6_C1": {"DPS": 11010}, "M6_V0_H3_C1": {"DPS": 11006}, "M0_V0_H7_C3": {"DPS": 10998}, "M6_V1_H3_C0": {"DPS": 10998}, "M3_V0_H4_C3": {"DPS": 10991}, "M0_V1_H7_C2": {"DPS": 10988}, "M2_V3_H5_C0": {"DPS": 10988}, "M0_V2_H8_C0": {"DPS": 10986}, "M3_V1_H4_C2": {"DPS": 10984}, "M1_V3_H6_C0": {"DPS": 10979}, "M5_V0_H3_C2": {"DPS": 10978}, "M3_V2_H4_C1": {"DPS": 10975}, "M5_V1_H3_C1": {"DPS": 10969}, "M0_V2_H7_C1": {"DPS": 10969}, "M1_V0_H5_C4": {"DPS": 10949}, "M3_V3_H4_C0": {"DPS": 10948}, "M1_V1_H5_C3": {"DPS": 10946}, "M5_V2_H3_C0": {"DPS": 10944}, "M0_V3_H7_C0": {"DPS": 10939}, "M0_V1_H6_C3": {"DPS": 10937}, "M0_V0_H6_C4": {"DPS": 10936}, "M1_V2_H5_C2": {"DPS": 10935}, "M4_V0_H3_C3": {"DPS": 10931}, "M4_V1_H3_C2": {"DPS": 10926}, "M0_V2_H6_C2": {"DPS": 10923}, "M2_V1_H4_C3": {"DPS": 10921}, "M2_V0_H4_C4": {"DPS": 10919}, "M1_V3_H5_C1": {"DPS": 10916}, "M4_V2_H3_C1": {"DPS": 10914}, "M2_V2_H4_C2": {"DPS": 10909}, "M0_V3_H6_C1": {"DPS": 10898}, "M7_V0_H2_C1": {"DPS": 10895}, "M2_V3_H4_C1": {"DPS": 10893}, "M4_V3_H3_C0": {"DPS": 10889}, "M1_V4_H5_C0": {"DPS": 10885}, "M8_V0_H2_C0": {"DPS": 10885}, "M7_V1_H2_C0": {"DPS": 10876}, "M6_V0_H2_C2": {"DPS": 10872}, "M3_V1_H3_C3": {"DPS": 10867}, "M0_V4_H6_C0": {"DPS": 10866}, "M3_V0_H3_C4": {"DPS": 10865}, "M6_V1_H2_C1": {"DPS": 10864}, "M2_V4_H4_C0": {"DPS": 10864}, "M3_V2_H3_C2": {"DPS": 10862}, "M0_V1_H5_C4": {"DPS": 10853}, "M0_V0_H5_C5": {"DPS": 10849}, "M0_V2_H5_C3": {"DPS": 10847}, "M3_V3_H3_C1": {"DPS": 10842}, "M6_V2_H2_C0": {"DPS": 10840}, "M5_V0_H2_C3": {"DPS": 10834}, "M1_V1_H4_C4": {"DPS": 10833}, "M5_V1_H2_C2": {"DPS": 10832}, "M1_V2_H4_C3": {"DPS": 10831}, "M1_V0_H4_C5": {"DPS": 10831}, "M0_V3_H5_C2": {"DPS": 10828}, "M5_V2_H2_C1": {"DPS": 10818}, "M3_V4_H3_C0": {"DPS": 10817}, "M1_V3_H4_C2": {"DPS": 10816}, "M0_V4_H5_C1": {"DPS": 10805}, "M2_V2_H3_C3": {"DPS": 10799}, "M2_V1_H3_C4": {"DPS": 10799}, "M1_V4_H4_C1": {"DPS": 10796}, "M2_V0_H3_C5": {"DPS": 10795}, "M5_V3_H2_C0": {"DPS": 10789}, "M4_V1_H2_C3": {"DPS": 10787}, "M4_V0_H2_C4": {"DPS": 10784}, "M2_V3_H3_C2": {"DPS": 10782}, "M4_V2_H2_C2": {"DPS": 10778}, "M0_V5_H5_C0": {"DPS": 10770}, "M8_V0_H1_C1": {"DPS": 10762}, "M7_V0_H1_C2": {"DPS": 10761}, "M4_V3_H2_C1": {"DPS": 10757}, "M2_V4_H3_C1": {"DPS": 10756}, "M1_V5_H4_C0": {"DPS": 10756}, "M7_V1_H1_C1": {"DPS": 10750}, "M8_V1_H1_C0": {"DPS": 10746}, "M6_V0_H1_C3": {"DPS": 10741}, "M9_V0_H1_C0": {"DPS": 10739}, "M6_V1_H1_C2": {"DPS": 10734}, "M0_V2_H4_C4": {"DPS": 10733}, "M0_V1_H4_C5": {"DPS": 10732}, "M7_V2_H1_C0": {"DPS": 10727}, "M0_V3_H4_C3": {"DPS": 10727}, "M4_V4_H2_C0": {"DPS": 10726}, "M2_V5_H3_C0": {"DPS": 10724}, "M3_V1_H2_C4": {"DPS": 10724}, "M0_V0_H4_C6": {"DPS": 10723}, "M3_V2_H2_C3": {"DPS": 10723}, "M3_V0_H2_C5": {"DPS": 10722}, "M6_V2_H1_C1": {"DPS": 10713}, "M1_V2_H3_C4": {"DPS": 10711}, "M3_V3_H2_C2": {"DPS": 10709}, "M0_V4_H4_C2": {"DPS": 10707}, "M1_V1_H3_C5": {"DPS": 10704}, "M1_V3_H3_C3": {"DPS": 10703}, "M5_V0_H1_C4": {"DPS": 10700}, "M1_V0_H3_C6": {"DPS": 10699}, "M5_V1_H1_C3": {"DPS": 10698}, "M5_V2_H1_C2": {"DPS": 10690}, "M6_V3_H1_C0": {"DPS": 10688}, "M1_V4_H3_C2": {"DPS": 10687}, "M3_V4_H2_C1": {"DPS": 10682}, "M0_V5_H4_C1": {"DPS": 10679}, "M5_V3_H1_C1": {"DPS": 10665}, "M2_V2_H2_C4": {"DPS": 10654}, "M2_V1_H2_C5": {"DPS": 10654}, "M1_V5_H3_C1": {"DPS": 10653}, "M4_V1_H1_C4": {"DPS": 10649}, "M3_V5_H2_C0": {"DPS": 10648}, "M2_V3_H2_C3": {"DPS": 10647}, "M4_V0_H1_C5": {"DPS": 10647}, "M4_V2_H1_C3": {"DPS": 10643}, "M2_V0_H2_C6": {"DPS": 10642}, "M0_V6_H4_C0": {"DPS": 10641}, "M5_V4_H1_C0": {"DPS": 10634}, "M4_V3_H1_C2": {"DPS": 10627}, "M2_V4_H2_C2": {"DPS": 10626}, "M1_V6_H3_C0": {"DPS": 10617}, "M0_V2_H3_C5": {"DPS": 10611}, "M4_V4_H1_C1": {"DPS": 10606}, "M0_V3_H3_C4": {"DPS": 10605}, "M0_V1_H3_C6": {"DPS": 10605}, "M2_V5_H2_C1": {"DPS": 10599}, "M0_V4_H3_C3": {"DPS": 10593}, "M0_V0_H3_C7": {"DPS": 10591}, "M3_V2_H1_C4": {"DPS": 10590}, "M3_V1_H1_C5": {"DPS": 10587}, "M8_V0_H0_C2": {"DPS": 10580}, "M3_V0_H1_C6": {"DPS": 10579}, "M3_V3_H1_C3": {"DPS": 10579}, "M7_V0_H0_C3": {"DPS": 10577}, "M0_V5_H3_C2": {"DPS": 10572}, "M4_V5_H1_C0": {"DPS": 10569}, "M7_V1_H0_C2": {"DPS": 10569}, "M1_V2_H2_C5": {"DPS": 10569}, "M8_V1_H0_C1": {"DPS": 10565}, "M9_V0_H0_C1": {"DPS": 10564}, "M1_V3_H2_C4": {"DPS": 10564}, "M1_V1_H2_C6": {"DPS": 10562}, "M3_V4_H1_C2": {"DPS": 10557}, "M2_V6_H2_C0": {"DPS": 10556}, "M7_V2_H0_C1": {"DPS": 10551}, "M1_V0_H2_C7": {"DPS": 10551}, "M1_V4_H2_C3": {"DPS": 10549}, "M6_V0_H0_C4": {"DPS": 10547}, "M6_V1_H0_C3": {"DPS": 10544}, "M9_V1_H0_C0": {"DPS": 10542}, "M8_V2_H0_C0": {"DPS": 10541}, "M0_V6_H3_C1": {"DPS": 10535}, "M6_V2_H0_C2": {"DPS": 10533}, "M1_V5_H2_C2": {"DPS": 10528}, "M3_V5_H1_C1": {"DPS": 10528}, "M10_V0_H0_C0": {"DPS": 10527}, "M7_V3_H0_C0": {"DPS": 10526}, "M2_V2_H1_C5": {"DPS": 10517}, "M6_V3_H0_C1": {"DPS": 10517}, "M2_V1_H1_C6": {"DPS": 10511}, "M5_V1_H0_C4": {"DPS": 10508}, "M2_V3_H1_C4": {"DPS": 10508}, "M5_V0_H0_C5": {"DPS": 10508}, "M5_V2_H0_C3": {"DPS": 10503}, "M2_V0_H1_C7": {"DPS": 10498}, "M0_V7_H3_C0": {"DPS": 10498}, "M2_V4_H1_C3": {"DPS": 10496}, "M1_V6_H2_C1": {"DPS": 10492}, "M3_V6_H1_C0": {"DPS": 10486}, "M5_V3_H0_C2": {"DPS": 10485}, "M6_V4_H0_C0": {"DPS": 10481}, "M2_V5_H1_C2": {"DPS": 10470}, "M0_V3_H2_C5": {"DPS": 10466}, "M0_V2_H2_C6": {"DPS": 10465}, "M4_V1_H0_C5": {"DPS": 10458}, "M5_V4_H0_C1": {"DPS": 10457}, "M0_V4_H2_C4": {"DPS": 10457}, "M0_V1_H2_C7": {"DPS": 10456}, "M4_V2_H0_C4": {"DPS": 10456}, "M4_V0_H0_C6": {"DPS": 10450}, "M4_V3_H0_C3": {"DPS": 10446}, "M1_V7_H2_C0": {"DPS": 10444}, "M0_V5_H2_C3": {"DPS": 10441}, "M2_V6_H1_C1": {"DPS": 10437}, "M1_V2_H1_C6": {"DPS": 10430}, "M1_V3_H1_C5": {"DPS": 10428}, "M5_V5_H0_C0": {"DPS": 10427}, "M0_V0_H2_C8": {"DPS": 10426}, "M4_V4_H0_C2": {"DPS": 10423}, "M1_V1_H1_C7": {"DPS": 10422}, "M1_V4_H1_C4": {"DPS": 10417}, "M0_V6_H2_C2": {"DPS": 10408}, "M3_V2_H0_C5": {"DPS": 10402}, "M1_V5_H1_C3": {"DPS": 10400}, "M4_V5_H0_C1": {"DPS": 10393}, "M3_V1_H0_C6": {"DPS": 10393}, "M1_V0_H1_C8": {"DPS": 10392}, "M3_V3_H0_C4": {"DPS": 10391}, "M2_V7_H1_C0": {"DPS": 10390}, "M3_V0_H0_C7": {"DPS": 10381}, "M0_V7_H2_C1": {"DPS": 10377}, "M3_V4_H0_C3": {"DPS": 10374}, "M1_V6_H1_C2": {"DPS": 10368}, "M4_V6_H0_C0": {"DPS": 10358}, "M3_V5_H0_C2": {"DPS": 10345}, "M1_V7_H1_C1": {"DPS": 10335}, "M0_V3_H1_C6": {"DPS": 10333}, "M0_V2_H1_C7": {"DPS": 10329}, "M2_V2_H0_C6": {"DPS": 10325}, "M0_V4_H1_C5": {"DPS": 10324}, "M0_V8_H2_C0": {"DPS": 10323}, "M2_V3_H0_C5": {"DPS": 10322}, "M2_V1_H0_C7": {"DPS": 10316}, "M3_V6_H0_C1": {"DPS": 10312}, "M2_V4_H0_C4": {"DPS": 10312}, "M0_V5_H1_C4": {"DPS": 10307}, "M0_V1_H1_C8": {"DPS": 10300}, "M2_V5_H0_C3": {"DPS": 10292}, "M2_V0_H0_C8": {"DPS": 10291}, "M0_V6_H1_C3": {"DPS": 10290}, "M1_V8_H1_C0": {"DPS": 10284}, "M3_V7_H0_C0": {"DPS": 10270}, "M0_V0_H1_C9": {"DPS": 10262}, "M2_V6_H0_C2": {"DPS": 10259}, "M0_V7_H1_C2": {"DPS": 10255}, "M1_V3_H0_C6": {"DPS": 10238}, "M1_V2_H0_C7": {"DPS": 10234}, "M1_V4_H0_C5": {"DPS": 10230}, "M2_V7_H0_C1": {"DPS": 10225}, "M1_V5_H0_C4": {"DPS": 10218}, "M1_V1_H0_C8": {"DPS": 10210}, "M0_V8_H1_C1": {"DPS": 10207}, "M1_V6_H0_C3": {"DPS": 10187}, "M2_V8_H0_C0": {"DPS": 10173}, "M1_V0_H0_C9": {"DPS": 10165}, "M1_V7_H0_C2": {"DPS": 10162}, "M0_V9_H1_C0": {"DPS": 10158}, "M0_V3_H0_C7": {"DPS": 10139}, "M0_V4_H0_C6": {"DPS": 10136}, "M0_V5_H0_C5": {"DPS": 10130}, "M0_V2_H0_C8": {"DPS": 10120}, "M1_V8_H0_C1": {"DPS": 10117}, "M0_V6_H0_C4": {"DPS": 10106}, "M0_V1_H0_C9": {"DPS": 10083}, "M0_V7_H0_C3": {"DPS": 10081}, "M1_V9_H0_C0": {"DPS": 10067}, "M0_V8_H0_C2": {"DPS": 10044}, "M0_V0_H0_C10": {"DPS": 10040}, "M0_V9_H0_C1": {"DPS": 9995}, "M0_V10_H0_C0": {"DPS": 9923}, "Base": {"DPS": 8074}}, "ids": {"M4_V0_H6_C0": null, "M3_V0_H7_C0": null, "M5_V0_H5_C0": null, "M2_V0_H8_C0": null, "M3_V0_H6_C1": null, "M2_V0_H7_C1": null, "M3_V1_H6_C0": null, "M4_V0_H5_C1": null, "M2_V1_H7_C0": null, "M4_V1_H5_C0": null, "M6_V0_H4_C0": null, "M1_V0_H8_C1": null, "M1_V0_H9_C0": null, "M2_V0_H6_C2": null, "M2_V1_H6_C1": null, "M3_V0_H5_C2": null, "M3_V1_H5_C1": null, "M1_V1_H8_C0": null, "M5_V0_H4_C1": null, "M1_V0_H7_C2": null, "M0_V0_H10_C0": null, "M5_V1_H4_C0": null, "M2_V2_H6_C0": null, "M1_V1_H7_C1": null, "M3_V2_H5_C0": null, "M4_V0_H4_C2": null, "M1_V2_H7_C0": null, "M4_V1_H4_C1": null, "M0_V0_H9_C1": null, "M2_V0_H5_C3": null, "M1_V0_H6_C3": null, "M2_V1_H5_C2": null, "M0_V0_H8_C2": null, "M7_V0_H3_C0": null, "M1_V1_H6_C2": null, "M4_V2_H4_C0": null, "M0_V1_H9_C0": null, "M2_V2_H5_C1": null, "M0_V1_H8_C1": null, "M1_V2_H6_C1": null, "M6_V0_H3_C1": null, "M0_V0_H7_C3": null, "M6_V1_H3_C0": null, "M3_V0_H4_C3": null, "M0_V1_H7_C2": null, "M2_V3_H5_C0": null, "M0_V2_H8_C0": null, "M3_V1_H4_C2": null, "M1_V3_H6_C0": null, "M5_V0_H3_C2": null, "M3_V2_H4_C1": null, "M5_V1_H3_C1": null, "M0_V2_H7_C1": null, "M1_V0_H5_C4": null, "M3_V3_H4_C0": null, "M1_V1_H5_C3": null, "M5_V2_H3_C0": null, "M0_V3_H7_C0": null, "M0_V1_H6_C3": null, "M0_V0_H6_C4": null, "M1_V2_H5_C2": null, "M4_V0_H3_C3": null, "M4_V1_H3_C2": null, "M0_V2_H6_C2": null, "M2_V1_H4_C3": null, "M2_V0_H4_C4": null, "M1_V3_H5_C1": null, "M4_V2_H3_C1": null, "M2_V2_H4_C2": null, "M0_V3_H6_C1": null, "M7_V0_H2_C1": null, "M2_V3_H4_C1": null, "M4_V3_H3_C0": null, "M1_V4_H5_C0": null, "M8_V0_H2_C0": null, "M7_V1_H2_C0": null, "M6_V0_H2_C2": null, "M3_V1_H3_C3": null, "M0_V4_H6_C0": null, "M3_V0_H3_C4": null, "M6_V1_H2_C1": null, "M2_V4_H4_C0": null, "M3_V2_H3_C2": null, "M0_V1_H5_C4": null, "M0_V0_H5_C5": null, "M0_V2_H5_C3": null, "M3_V3_H3_C1": null, "M6_V2_H2_C0": null, "M5_V0_H2_C3": null, "M1_V1_H4_C4": null, "M5_V1_H2_C2": null, "M1_V2_H4_C3": null, "M1_V0_H4_C5": null, "M0_V3_H5_C2": null, "M5_V2_H2_C1": null, "M3_V4_H3_C0": null, "M1_V3_H4_C2": null, "M0_V4_H5_C1": null, "M2_V2_H3_C3": null, "M2_V1_H3_C4": null, "M1_V4_H4_C1": null, "M2_V0_H3_C5": null, "M5_V3_H2_C0": null, "M4_V1_H2_C3": null, "M4_V0_H2_C4": null, "M2_V3_H3_C2": null, "M4_V2_H2_C2": null, "M0_V5_H5_C0": null, "M8_V0_H1_C1": null, "M7_V0_H1_C2": null, "M4_V3_H2_C1": null, "M2_V4_H3_C1": null, "M1_V5_H4_C0": null, "M7_V1_H1_C1": null, "M8_V1_H1_C0": null, "M6_V0_H1_C3": null, "M9_V0_H1_C0": null, "M6_V1_H1_C2": null, "M0_V2_H4_C4": null, "M0_V1_H4_C5": null, "M7_V2_H1_C0": null, "M0_V3_H4_C3": null, "M4_V4_H2_C0": null, "M2_V5_H3_C0": null, "M3_V1_H2_C4": null, "M0_V0_H4_C6": null, "M3_V2_H2_C3": null, "M3_V0_H2_C5": null, "M6_V2_H1_C1": null, "M1_V2_H3_C4": null, "M3_V3_H2_C2": null, "M0_V4_H4_C2": null, "M1_V1_H3_C5": null, "M1_V3_H3_C3": null, "M5_V0_H1_C4": null, "M1_V0_H3_C6": null, "M5_V1_H1_C3": null, "M5_V2_H1_C2": null, "M6_V3_H1_C0": null, "M1_V4_H3_C2": null, "M3_V4_H2_C1": null, "M0_V5_H4_C1": null, "M5_V3_H1_C1": null, "M2_V2_H2_C4": null, "M2_V1_H2_C5": null, "M1_V5_H3_C1": null, "M4_V1_H1_C4": null, "M3_V5_H2_C0": null, "M2_V3_H2_C3": null, "M4_V0_H1_C5": null, "M4_V2_H1_C3": null, "M2_V0_H2_C6": null, "M0_V6_H4_C0": null, "M5_V4_H1_C0": null, "M4_V3_H1_C2": null, "M2_V4_H2_C2": null, "M1_V6_H3_C0": null, "M0_V2_H3_C5": null, "M4_V4_H1_C1": null, "M0_V3_H3_C4": null, "M0_V1_H3_C6": null, "M2_V5_H2_C1": null, "M0_V4_H3_C3": null, "M0_V0_H3_C7": null, "M3_V2_H1_C4": null, "M3_V1_H1_C5": null, "M8_V0_H0_C2": null, "M3_V0_H1_C6": null, "M3_V3_H1_C3": null, "M7_V0_H0_C3": null, "M0_V5_H3_C2": null, "M4_V5_H1_C0": null, "M7_V1_H0_C2": null, "M1_V2_H2_C5": null, "M8_V1_H0_C1": null, "M9_V0_H0_C1": null, "M1_V3_H2_C4": null, "M1_V1_H2_C6": null, "M3_V4_H1_C2": null, "M2_V6_H2_C0": null, "M7_V2_H0_C1": null, "M1_V0_H2_C7": null, "M1_V4_H2_C3": null, "M6_V0_H0_C4": null, "M6_V1_H0_C3": null, "M9_V1_H0_C0": null, "M8_V2_H0_C0": null, "M0_V6_H3_C1": null, "M6_V2_H0_C2": null, "M1_V5_H2_C2": null, "M3_V5_H1_C1": null, "M10_V0_H0_C0": null, "M7_V3_H0_C0": null, "M2_V2_H1_C5": null, "M6_V3_H0_C1": null, "M2_V1_H1_C6": null, "M5_V1_H0_C4": null, "M2_V3_H1_C4": null, "M5_V0_H0_C5": null, "M5_V2_H0_C3": null, "M2_V0_H1_C7": null, "M0_V7_H3_C0": null, "M2_V4_H1_C3": null, "M1_V6_H2_C1": null, "M3_V6_H1_C0": null, "M5_V3_H0_C2": null, "M6_V4_H0_C0": null, "M2_V5_H1_C2": null, "M0_V3_H2_C5": null, "M0_V2_H2_C6": null, "M4_V1_H0_C5": null, "M5_V4_H0_C1": null, "M0_V4_H2_C4": null, "M0_V1_H2_C7": null, "M4_V2_H0_C4": null, "M4_V0_H0_C6": null, "M4_V3_H0_C3": null, "M1_V7_H2_C0": null, "M0_V5_H2_C3": null, "M2_V6_H1_C1": null, "M1_V2_H1_C6": null, "M1_V3_H1_C5": null, "M5_V5_H0_C0": null, "M0_V0_H2_C8": null, "M4_V4_H0_C2": null, "M1_V1_H1_C7": null, "M1_V4_H1_C4": null, "M0_V6_H2_C2": null, "M3_V2_H0_C5": null, "M1_V5_H1_C3": null, "M4_V5_H0_C1": null, "M3_V1_H0_C6": null, "M1_V0_H1_C8": null, "M3_V3_H0_C4": null, "M2_V7_H1_C0": null, "M3_V0_H0_C7": null, "M0_V7_H2_C1": null, "M3_V4_H0_C3": null, "M1_V6_H1_C2": null, "M4_V6_H0_C0": null, "M3_V5_H0_C2": null, "M1_V7_H1_C1": null, "M0_V3_H1_C6": null, "M0_V2_H1_C7": null, "M2_V2_H0_C6": null, "M0_V4_H1_C5": null, "M0_V8_H2_C0": null, "M2_V3_H0_C5": null, "M2_V1_H0_C7": null, "M3_V6_H0_C1": null, "M2_V4_H0_C4": null, "M0_V5_H1_C4": null, "M0_V1_H1_C8": null, "M2_V5_H0_C3": null, "M2_V0_H0_C8": null, "M0_V6_H1_C3": null, "M1_V8_H1_C0": null, "M3_V7_H0_C0": null, "M0_V0_H1_C9": null, "M2_V6_H0_C2": null, "M0_V7_H1_C2": null, "M1_V3_H0_C6": null, "M1_V2_H0_C7": null, "M1_V4_H0_C5": null, "M2_V7_H0_C1": null, "M1_V5_H0_C4": null, "M1_V1_H0_C8": null, "M0_V8_H1_C1": null, "M1_V6_H0_C3": null, "M2_V8_H0_C0": null, "M1_V0_H0_C9": null, "M1_V7_H0_C2": null, "M0_V9_H1_C0": null, "M0_V3_H0_C7": null, "M0_V4_H0_C6": null, "M0_V5_H0_C5": null, "M0_V2_H0_C8": null, "M1_V8_H0_C1": null, "M0_V6_H0_C4": null, "M0_V1_H0_C9": null, "M0_V7_H0_C3": null, "M1_V9_H0_C0": null, "M0_V8_H0_C2": null, "M0_V0_H0_C10": null, "M0_V9_H0_C1": null, "M0_V10_H0_C0": null}, "simulated_steps": ["DPS"], "sorted_data_keys": ["M4_V0_H6_C0", "M3_V0_H7_C0", "M5_V0_H5_C0", "M2_V0_H8_C0", "M3_V0_H6_C1", "M2_V0_H7_C1", "M3_V1_H6_C0", "M4_V0_H5_C1", "M2_V1_H7_C0", "M4_V1_H5_C0", "M6_V0_H4_C0", "M1_V0_H8_C1", "M1_V0_H9_C0", "M2_V0_H6_C2", "M2_V1_H6_C1", "M3_V0_H5_C2", "M3_V1_H5_C1", "M1_V1_H8_C0", "M5_V0_H4_C1", "M1_V0_H7_C2", "M0_V0_H10_C0", "M5_V1_H4_C0", "M2_V2_H6_C0", "M1_V1_H7_C1", "M3_V2_H5_C0", "M4_V0_H4_C2", "M1_V2_H7_C0", "M4_V1_H4_C1", "M0_V0_H9_C1", "M2_V0_H5_C3", "M1_V0_H6_C3", "M2_V1_H5_C2", "M0_V0_H8_C2", "M7_V0_H3_C0", "M1_V1_H6_C2", "M4_V2_H4_C0", "M0_V1_H9_C0", "M2_V2_H5_C1", "M0_V1_H8_C1", "M1_V2_H6_C1", "M6_V0_H3_C1", "M0_V0_H7_C3", "M6_V1_H3_C0", "M3_V0_H4_C3", "M0_V1_H7_C2", "M2_V3_H5_C0", "M0_V2_H8_C0", "M3_V1_H4_C2", "M1_V3_H6_C0", "M5_V0_H3_C2", "M3_V2_H4_C1", "M5_V1_H3_C1", "M0_V2_H7_C1", "M1_V0_H5_C4", "M3_V3_H4_C0", "M1_V1_H5_C3", "M5_V2_H3_C0", "M0_V3_H7_C0", "M0_V1_H6_C3", "M0_V0_H6_C4", "M1_V2_H5_C2", "M4_V0_H3_C3", "M4_V1_H3_C2", "M0_V2_H6_C2", "M2_V1_H4_C3", "M2_V0_H4_C4", "M1_V3_H5_C1", "M4_V2_H3_C1", "M2_V2_H4_C2", "M0_V3_H6_C1", "M7_V0_H2_C1", "M2_V3_H4_C1", "M4_V3_H3_C0", "M1_V4_H5_C0", "M8_V0_H2_C0", "M7_V1_H2_C0", "M6_V0_H2_C2", "M3_V1_H3_C3", "M0_V4_H6_C0", "M3_V0_H3_C4", "M6_V1_H2_C1", "M2_V4_H4_C0", "M3_V2_H3_C2", "M0_V1_H5_C4", "M0_V0_H5_C5", "M0_V2_H5_C3", "M3_V3_H3_C1", "M6_V2_H2_C0", "M5_V0_H2_C3", "M1_V1_H4_C4", "M5_V1_H2_C2", "M1_V2_H4_C3", "M1_V0_H4_C5", "M0_V3_H5_C2", "M5_V2_H2_C1", "M3_V4_H3_C0", "M1_V3_H4_C2", "M0_V4_H5_C1", "M2_V2_H3_C3", "M2_V1_H3_C4", "M1_V4_H4_C1", "M2_V0_H3_C5", "M5_V3_H2_C0", "M4_V1_H2_C3", "M4_V0_H2_C4", "M2_V3_H3_C2", "M4_V2_H2_C2", "M0_V5_H5_C0", "M8_V0_H1_C1", "M7_V0_H1_C2", "M4_V3_H2_C1", "M2_V4_H3_C1", "M1_V5_H4_C0", "M7_V1_H1_C1", "M8_V1_H1_C0", "M6_V0_H1_C3", "M9_V0_H1_C0", "M6_V1_H1_C2", "M0_V2_H4_C4", "M0_V1_H4_C5", "M7_V2_H1_C0", "M0_V3_H4_C3", "M4_V4_H2_C0", "M2_V5_H3_C0", "M3_V1_H2_C4", "M0_V0_H4_C6", "M3_V2_H2_C3", "M3_V0_H2_C5", "M6_V2_H1_C1", "M1_V2_H3_C4", "M3_V3_H2_C2", "M0_V4_H4_C2", "M1_V1_H3_C5", "M1_V3_H3_C3", "M5_V0_H1_C4", "M1_V0_H3_C6", "M5_V1_H1_C3", "M5_V2_H1_C2", "M6_V3_H1_C0", "M1_V4_H3_C2", "M3_V4_H2_C1", "M0_V5_H4_C1", "M5_V3_H1_C1", "M2_V2_H2_C4", "M2_V1_H2_C5", "M1_V5_H3_C1", "M4_V1_H1_C4", "M3_V5_H2_C0", "M2_V3_H2_C3", "M4_V0_H1_C5", "M4_V2_H1_C3", "M2_V0_H2_C6", "M0_V6_H4_C0", "M5_V4_H1_C0", "M4_V3_H1_C2", "M2_V4_H2_C2", "M1_V6_H3_C0", "M0_V2_H3_C5", "M4_V4_H1_C1", "M0_V3_H3_C4", "M0_V1_H3_C6", "M2_V5_H2_C1", "M0_V4_H3_C3", "M0_V0_H3_C7", "M3_V2_H1_C4", "M3_V1_H1_C5", "M8_V0_H0_C2", "M3_V0_H1_C6", "M3_V3_H1_C3", "M7_V0_H0_C3", "M0_V5_H3_C2", "M4_V5_H1_C0", "M7_V1_H0_C2", "M1_V2_H2_C5", "M8_V1_H0_C1", "M9_V0_H0_C1", "M1_V3_H2_C4", "M1_V1_H2_C6", "M3_V4_H1_C2", "M2_V6_H2_C0", "M7_V2_H0_C1", "M1_V0_H2_C7", "M1_V4_H2_C3", "M6_V0_H0_C4", "M6_V1_H0_C3", "M9_V1_H0_C0", "M8_V2_H0_C0", "M0_V6_H3_C1", "M6_V2_H0_C2", "M1_V5_H2_C2", "M3_V5_H1_C1", "M10_V0_H0_C0", "M7_V3_H0_C0", "M2_V2_H1_C5", "M6_V3_H0_C1", "M2_V1_H1_C6", "M5_V1_H0_C4", "M2_V3_H1_C4", "M5_V0_H0_C5", "M5_V2_H0_C3", "M2_V0_H1_C7", "M0_V7_H3_C0", "M2_V4_H1_C3", "M1_V6_H2_C1", "M3_V6_H1_C0", "M5_V3_H0_C2", "M6_V4_H0_C0", "M2_V5_H1_C2", "M0_V3_H2_C5", "M0_V2_H2_C6", "M4_V1_H0_C5", "M5_V4_H0_C1", "M0_V4_H2_C4", "M0_V1_H2_C7", "M4_V2_H0_C4", "M4_V0_H0_C6", "M4_V3_H0_C3", "M1_V7_H2_C0", "M0_V5_H2_C3", "M2_V6_H1_C1", "M1_V2_H1_C6", "M1_V3_H1_C5", "M5_V5_H0_C0", "M0_V0_H2_C8", "M4_V4_H0_C2", "M1_V1_H1_C7", "M1_V4_H1_C4", "M0_V6_H2_C2", "M3_V2_H0_C5", "M1_V5_H1_C3", "M4_V5_H0_C1", "M3_V1_H0_C6", "M1_V0_H1_C8", "M3_V3_H0_C4", "M2_V7_H1_C0", "M3_V0_H0_C7", "M0_V7_H2_C1", "M3_V4_H0_C3", "M1_V6_H1_C2", "M4_V6_H0_C0", "M3_V5_H0_C2", "M1_V7_H1_C1", "M0_V3_H1_C6", "M0_V2_H1_C7", "M2_V2_H0_C6", "M0_V4_H1_C5", "M0_V8_H2_C0", "M2_V3_H0_C5", "M2_V1_H0_C7", "M3_V6_H0_C1", "M2_V4_H0_C4", "M0_V5_H1_C4", "M0_V1_H1_C8", "M2_V5_H0_C3", "M2_V0_H0_C8", "M0_V6_H1_C3", "M1_V8_H1_C0", "M3_V7_H0_C0", "M0_V0_H1_C9", "M2_V6_H0_C2", "M0_V7_H1_C2", "M1_V3_H0_C6", "M1_V2_H0_C7", "M1_V4_H0_C5", "M2_V7_H0_C1", "M1_V5_H0_C4", "M1_V1_H0_C8", "M0_V8_H1_C1", "M1_V6_H0_C3", "M2_V8_H0_C0", "M1_V0_H0_C9", "M1_V7_H0_C2", "M0_V9_H1_C0", "M0_V3_H0_C7", "M0_V4_H0_C6", "M0_V5_H0_C5", "M0_V2_H0_C8", "M1_V8_H0_C1", "M0_V6_H0_C4", "M0_V1_H0_C9", "M0_V7_H0_C3", "M1_V9_H0_C0", "M0_V8_H0_C2", "M0_V0_H0_C10", "M0_V9_H0_C1", "M0_V10_H0_C0"], "last_updated": "2022-02-11"}