{"name": "Dungeons - hv-sc - venthyr", "data": {"Eternal_Call_to_the_Void_Hands_HC": {"235": 6953, "225": 6916, "210": 6882, "190": 6820}, "Eternal_Call_to_the_Void_Wrists_HM": {"235": 6952, "225": 6921, "210": 6885, "190": 6845}, "Eternal_Call_to_the_Void_Hands_HM": {"235": 6947, "225": 6910, "210": 6879, "190": 6820}, "Eternal_Call_to_the_Void_Wrists_HC": {"235": 6945, "225": 6919, "210": 6903, "190": 6850}, "Shadowflame_Prism_Conduit_Head_HC": {"235": 6921, "225": 6877, "210": 6809, "190": 6746}, "Shadowflame_Prism_Mindbender_Conduit_Head_HM": {"235": 6915, "225": 6872, "210": 6812, "190": 6745}, "Shadowflame_Prism_Mindbender_Conduit_Head_HC": {"235": 6914, "225": 6879, "210": 6804, "190": 6738}, "Shadowflame_Prism_Conduit_Head_HM": {"235": 6911, "225": 6871, "210": 6811, "190": 6750}, "Shadowflame_Prism_Mindbender_Conduit_Hands_HC": {"235": 6901, "225": 6865, "210": 6828, "190": 6775}, "Shadowflame_Prism_Conduit_Hands_HM": {"235": 6898, "225": 6866, "210": 6824, "190": 6766}, "Shadowflame_Prism_Conduit_Hands_HC": {"235": 6897, "225": 6867, "210": 6826, "190": 6778}, "Shadowflame_Prism_Mindbender_Conduit_Hands_HM": {"235": 6894, "225": 6862, "210": 6817, "190": 6766}, "Shadowflame_Prism_Head_HC": {"235": 6848, "225": 6810, "210": 6744, "190": 6689}, "Shadowflame_Prism_Mindbender_Head_HM": {"235": 6844, "225": 6805, "210": 6745, "190": 6682}, "Shadowflame_Prism_Mindbender_Head_HC": {"235": 6841, "225": 6809, "210": 6753, "190": 6685}, "Shadowflame_Prism_Head_HM": {"235": 6838, "225": 6808, "210": 6747, "190": 6683}, "Shadowflame_Prism_Hands_HC": {"235": 6830, "225": 6800, "210": 6763, "190": 6707}, "Shadowflame_Prism_Hands_HM": {"235": 6830, "225": 6798, "210": 6760, "190": 6698}, "Shadowflame_Prism_Mindbender_Hands_HC": {"235": 6830, "225": 6798, "210": 6756, "190": 6699}, "Shadowflame_Prism_Mindbender_Hands_HM": {"235": 6830, "225": 6792, "210": 6757, "190": 6697}, "Talbadars_Stratagem_Conduit_Legs_HC": {"235": 6749, "225": 6710, "210": 6656, "190": 6589}, "Talbadars_Stratagem_Conduit_Legs_HM": {"235": 6748, "225": 6713, "210": 6651, "190": 6583}, "Talbadars_Stratagem_Legs_HC": {"235": 6746, "225": 6703, "210": 6655, "190": 6579}, "Talbadars_Stratagem_Legs_HM": {"235": 6744, "225": 6707, "210": 6652, "190": 6580}, "Talbadars_Stratagem_Conduit_Waist_HC": {"235": 6727, "225": 6695, "210": 6662, "190": 6599}, "Talbadars_Stratagem_Waist_HC": {"235": 6727, "225": 6693, "210": 6663, "190": 6594}, "Talbadars_Stratagem_Waist_HM": {"235": 6725, "225": 6683, "210": 6653, "190": 6585}, "Talbadars_Stratagem_Conduit_Waist_HM": {"235": 6721, "225": 6696, "210": 6652, "190": 6598}, "Painbreaker_Psalm_Chest_HC": {"235": 6715, "225": 6669, "210": 6619, "190": 6547}, "Painbreaker_Psalm_Back_HM": {"235": 6710, "225": 6686, "210": 6651, "190": 6614}, "Painbreaker_Psalm_Back_HC": {"235": 6708, "225": 6683, "210": 6646, "190": 6616}, "Painbreaker_Psalm_Chest_HM": {"235": 6701, "225": 6657, "210": 6607, "190": 6532}, "Sephuzs_Proclamation_Chest_HC": {"235": 6664, "225": 6614, "210": 6560, "190": 6488}, "Sephuzs_Proclamation_Shoulder_HC": {"235": 6661, "225": 6629, "210": 6588, "190": 6528}, "Sephuzs_Proclamation_Shoulder_HM": {"235": 6659, "225": 6620, "210": 6578, "190": 6529}, "Sephuzs_Proclamation_Chest_HM": {"235": 6656, "225": 6603, "210": 6548, "190": 6480}, "Echo_of_Eonar_Waist_HC": {"235": 6633, "225": 6597, "210": 6561, "190": 6495}, "Echo_of_Eonar_Wrists_HC": {"235": 6624, "225": 6598, "210": 6565, "190": 6525}, "Echo_of_Eonar_Waist_HM": {"235": 6621, "225": 6583, "210": 6550, "190": 6489}, "Twins_of_the_Sun_Priestess_Conduit_7_Head_HC": {"235": 6617, "225": 6574, "210": 6516, "190": 6447}, "Echo_of_Eonar_Wrists_HM": {"235": 6616, "225": 6587, "210": 6562, "190": 6528}, "Judgment_of_the_Arbiter_Hands_HC": {"235": 6616, "225": 6588, "210": 6553, "190": 6495}, "Twins_of_the_Sun_Priestess_Conduit_7_Head_HM": {"235": 6614, "225": 6574, "210": 6510, "190": 6445}, "Judgment_of_the_Arbiter_Wrists_HM": {"235": 6610, "225": 6580, "210": 6553, "190": 6517}, "Judgment_of_the_Arbiter_Hands_HM": {"235": 6609, "225": 6574, "210": 6542, "190": 6487}, "Judgment_of_the_Arbiter_Wrists_HC": {"235": 6608, "225": 6585, "210": 6561, "190": 6514}, "Echo_of_Eonar_Finger_HC": {"235": 6601, "225": 6569, "210": 6534, "190": 6481}, "Judgment_of_the_Arbiter_Finger_HC": {"235": 6594, "225": 6564, "210": 6523, "190": 6469}, "Echo_of_Eonar_Finger_HM": {"235": 6591, "225": 6563, "210": 6524, "190": 6470}, "Judgment_of_the_Arbiter_Finger_HM": {"235": 6575, "225": 6556, "210": 6512, "190": 6464}, "Sephuzs_Proclamation_Neck_HC": {"235": 6568, "225": 6572, "210": 6570, "190": 6560}, "Sephuzs_Proclamation_Neck_HM": {"235": 6568, "225": 6568, "210": 6567, "190": 6568}, "Twins_of_the_Sun_Priestess_Conduit_7_Shoulder_HC": {"235": 6553, "225": 6520, "210": 6478, "190": 6415}, "Third_Eye_of_the_Jailer_Head_HC": {"235": 6552, "225": 6509, "210": 6447, "190": 6392}, "Third_Eye_of_the_Jailer_Head_HM": {"235": 6547, "225": 6505, "210": 6442, "190": 6383}, "Twins_of_the_Sun_Priestess_Conduit_7_Shoulder_HM": {"235": 6547, "225": 6516, "210": 6474, "190": 6412}, "Third_Eye_of_the_Jailer_Waist_HC": {"235": 6525, "225": 6497, "210": 6456, "190": 6395}, "Third_Eye_of_the_Jailer_Waist_HM": {"235": 6524, "225": 6484, "210": 6453, "190": 6391}, "Third_Eye_of_the_Jailer_Shoulder_HC": {"235": 6499, "225": 6470, "210": 6434, "190": 6370}, "Third_Eye_of_the_Jailer_Shoulder_HM": {"235": 6496, "225": 6462, "210": 6431, "190": 6368}, "Base": {"DPS": 6492}}, "ids": {"Eternal_Call_to_the_Void_Hands_HC": 336214, "Eternal_Call_to_the_Void_Wrists_HM": 336214, "Eternal_Call_to_the_Void_Hands_HM": 336214, "Eternal_Call_to_the_Void_Wrists_HC": 336214, "Shadowflame_Prism_Conduit_Head_HC": 336143, "Shadowflame_Prism_Mindbender_Conduit_Head_HM": 336143, "Shadowflame_Prism_Mindbender_Conduit_Head_HC": 336143, "Shadowflame_Prism_Conduit_Head_HM": 336143, "Shadowflame_Prism_Mindbender_Conduit_Hands_HC": 336143, "Shadowflame_Prism_Conduit_Hands_HM": 336143, "Shadowflame_Prism_Conduit_Hands_HC": 336143, "Shadowflame_Prism_Mindbender_Conduit_Hands_HM": 336143, "Shadowflame_Prism_Head_HC": 336143, "Shadowflame_Prism_Mindbender_Head_HM": 336143, "Shadowflame_Prism_Mindbender_Head_HC": 336143, "Shadowflame_Prism_Head_HM": 336143, "Shadowflame_Prism_Hands_HC": 336143, "Shadowflame_Prism_Hands_HM": 336143, "Shadowflame_Prism_Mindbender_Hands_HC": 336143, "Shadowflame_Prism_Mindbender_Hands_HM": 336143, "Talbadars_Stratagem_Conduit_Legs_HC": 342415, "Talbadars_Stratagem_Conduit_Legs_HM": 342415, "Talbadars_Stratagem_Legs_HC": 342415, "Talbadars_Stratagem_Legs_HM": 342415, "Talbadars_Stratagem_Conduit_Waist_HC": 342415, "Talbadars_Stratagem_Waist_HC": 342415, "Talbadars_Stratagem_Waist_HM": 342415, "Talbadars_Stratagem_Conduit_Waist_HM": 342415, "Painbreaker_Psalm_Chest_HC": 336165, "Painbreaker_Psalm_Back_HM": 336165, "Painbreaker_Psalm_Back_HC": 336165, "Painbreaker_Psalm_Chest_HM": 336165, "Sephuzs_Proclamation_Chest_HC": 339348, "Sephuzs_Proclamation_Shoulder_HC": 339348, "Sephuzs_Proclamation_Shoulder_HM": 339348, "Sephuzs_Proclamation_Chest_HM": 339348, "Echo_of_Eonar_Waist_HC": 338477, "Echo_of_Eonar_Wrists_HC": 338477, "Echo_of_Eonar_Waist_HM": 338477, "Twins_of_the_Sun_Priestess_Conduit_7_Head_HC": 336897, "Echo_of_Eonar_Wrists_HM": 338477, "Judgment_of_the_Arbiter_Hands_HC": 339344, "Twins_of_the_Sun_Priestess_Conduit_7_Head_HM": 336897, "Judgment_of_the_Arbiter_Wrists_HM": 339344, "Judgment_of_the_Arbiter_Hands_HM": 339344, "Judgment_of_the_Arbiter_Wrists_HC": 339344, "Echo_of_Eonar_Finger_HC": 338477, "Judgment_of_the_Arbiter_Finger_HC": 339344, "Echo_of_Eonar_Finger_HM": 338477, "Judgment_of_the_Arbiter_Finger_HM": 339344, "Sephuzs_Proclamation_Neck_HC": 339348, "Sephuzs_Proclamation_Neck_HM": 339348, "Twins_of_the_Sun_Priestess_Conduit_7_Shoulder_HC": 336897, "Third_Eye_of_the_Jailer_Head_HC": 339058, "Third_Eye_of_the_Jailer_Head_HM": 339058, "Twins_of_the_Sun_Priestess_Conduit_7_Shoulder_HM": 336897, "Third_Eye_of_the_Jailer_Waist_HC": 339058, "Third_Eye_of_the_Jailer_Waist_HM": 339058, "Third_Eye_of_the_Jailer_Shoulder_HC": 339058, "Third_Eye_of_the_Jailer_Shoulder_HM": 339058}, "simulated_steps": [235, 225, 210, 190], "sorted_data_keys": ["Eternal_Call_to_the_Void_Hands_HC", "Eternal_Call_to_the_Void_Wrists_HM", "Eternal_Call_to_the_Void_Hands_HM", "Eternal_Call_to_the_Void_Wrists_HC", "Shadowflame_Prism_Conduit_Head_HC", "Shadowflame_Prism_Mindbender_Conduit_Head_HM", "Shadowflame_Prism_Mindbender_Conduit_Head_HC", "Shadowflame_Prism_Conduit_Head_HM", "Shadowflame_Prism_Mindbender_Conduit_Hands_HC", "Shadowflame_Prism_Conduit_Hands_HM", "Shadowflame_Prism_Conduit_Hands_HC", "Shadowflame_Prism_Mindbender_Conduit_Hands_HM", "Shadowflame_Prism_Head_HC", "Shadowflame_Prism_Mindbender_Head_HM", "Shadowflame_Prism_Mindbender_Head_HC", "Shadowflame_Prism_Head_HM", "Shadowflame_Prism_Hands_HC", "Shadowflame_Prism_Hands_HM", "Shadowflame_Prism_Mindbender_Hands_HC", "Shadowflame_Prism_Mindbender_Hands_HM", "Talbadars_Stratagem_Conduit_Legs_HC", "Talbadars_Stratagem_Conduit_Legs_HM", "Talbadars_Stratagem_Legs_HC", "Talbadars_Stratagem_Legs_HM", "Talbadars_Stratagem_Conduit_Waist_HC", "Talbadars_Stratagem_Waist_HC", "Talbadars_Stratagem_Waist_HM", "Talbadars_Stratagem_Conduit_Waist_HM", "Painbreaker_Psalm_Chest_HC", "Painbreaker_Psalm_Back_HM", "Painbreaker_Psalm_Back_HC", "Painbreaker_Psalm_Chest_HM", "Sephuzs_Proclamation_Chest_HC", "Sephuzs_Proclamation_Shoulder_HC", "Sephuzs_Proclamation_Shoulder_HM", "Sephuzs_Proclamation_Chest_HM", "Echo_of_Eonar_Waist_HC", "Echo_of_Eonar_Wrists_HC", "Echo_of_Eonar_Waist_HM", "Twins_of_the_Sun_Priestess_Conduit_7_Head_HC", "Echo_of_Eonar_Wrists_HM", "Judgment_of_the_Arbiter_Hands_HC", "Twins_of_the_Sun_Priestess_Conduit_7_Head_HM", "Judgment_of_the_Arbiter_Wrists_HM", "Judgment_of_the_Arbiter_Hands_HM", "Judgment_of_the_Arbiter_Wrists_HC", "Echo_of_Eonar_Finger_HC", "Judgment_of_the_Arbiter_Finger_HC", "Echo_of_Eonar_Finger_HM", "Judgment_of_the_Arbiter_Finger_HM", "Sephuzs_Proclamation_Neck_HC", "Sephuzs_Proclamation_Neck_HM", "Twins_of_the_Sun_Priestess_Conduit_7_Shoulder_HC", "Third_Eye_of_the_Jailer_Head_HC", "Third_Eye_of_the_Jailer_Head_HM", "Twins_of_the_Sun_Priestess_Conduit_7_Shoulder_HM", "Third_Eye_of_the_Jailer_Waist_HC", "Third_Eye_of_the_Jailer_Waist_HM", "Third_Eye_of_the_Jailer_Shoulder_HC", "Third_Eye_of_the_Jailer_Shoulder_HM"], "last_updated": "2021-03-07"}