{"name": "Composite - hv-sc - kyrian", "data": {"Shadowflame_Prism_Mindbender_Hands_HM": {"235": 7233, "225": 7198, "210": 7156, "190": 7097}, "Shadowflame_Prism_Mindbender_Head_HM": {"235": 7230, "225": 7184, "210": 7122, "190": 7051}, "Shadowflame_Prism_Mindbender_Conduit_Hands_HM": {"235": 7225, "225": 7188, "210": 7150, "190": 7091}, "Shadowflame_Prism_Mindbender_Hands_HC": {"235": 7225, "225": 7190, "210": 7150, "190": 7092}, "Shadowflame_Prism_Mindbender_Conduit_Head_HM": {"235": 7216, "225": 7172, "210": 7111, "190": 7040}, "Shadowflame_Prism_Mindbender_Conduit_Hands_HC": {"235": 7215, "225": 7181, "210": 7142, "190": 7086}, "Shadowflame_Prism_Mindbender_Head_HC": {"235": 7213, "225": 7169, "210": 7107, "190": 7039}, "Shadowflame_Prism_Mindbender_Conduit_Head_HC": {"235": 7198, "225": 7156, "210": 7094, "190": 7026}, "Talbadars_Stratagem_Waist_HM": {"235": 7077, "225": 7040, "210": 7003, "190": 6929}, "Talbadars_Stratagem_Waist_HC": {"235": 7069, "225": 7032, "210": 6995, "190": 6923}, "Talbadars_Stratagem_Legs_HM": {"235": 7068, "225": 7028, "210": 6970, "190": 6898}, "Talbadars_Stratagem_Legs_HC": {"235": 7052, "225": 7011, "210": 6955, "190": 6887}, "Talbadars_Stratagem_Conduit_Waist_HM": {"235": 7028, "225": 6991, "210": 6953, "190": 6883}, "Talbadars_Stratagem_Conduit_Legs_HM": {"235": 7020, "225": 6979, "210": 6920, "190": 6850}, "Talbadars_Stratagem_Conduit_Waist_HC": {"235": 7019, "225": 6982, "210": 6946, "190": 6876}, "Talbadars_Stratagem_Conduit_Legs_HC": {"235": 7003, "225": 6961, "210": 6904, "190": 6837}, "Eternal_Call_to_the_Void_Hands_HM": {"235": 6973, "225": 6941, "210": 6904, "190": 6844}, "Eternal_Call_to_the_Void_Wrists_HM": {"235": 6970, "225": 6941, "210": 6911, "190": 6870}, "Eternal_Call_to_the_Void_Hands_HC": {"235": 6964, "225": 6932, "210": 6895, "190": 6838}, "Eternal_Call_to_the_Void_Wrists_HC": {"235": 6961, "225": 6934, "210": 6904, "190": 6865}, "Shadowflame_Prism_Hands_HM": {"235": 6955, "225": 6923, "210": 6885, "190": 6827}, "Shadowflame_Prism_Hands_HC": {"235": 6947, "225": 6914, "210": 6877, "190": 6820}, "Shadowflame_Prism_Head_HM": {"235": 6943, "225": 6898, "210": 6841, "190": 6776}, "Shadowflame_Prism_Head_HC": {"235": 6927, "225": 6883, "210": 6827, "190": 6762}, "Echo_of_Eonar_Waist_HM": {"235": 6840, "225": 6804, "210": 6768, "190": 6696}, "Shadowflame_Prism_Conduit_Hands_HM": {"235": 6839, "225": 6808, "210": 6771, "190": 6715}, "Judgment_of_the_Arbiter_Hands_HM": {"235": 6832, "225": 6800, "210": 6763, "190": 6709}, "Echo_of_Eonar_Wrists_HM": {"235": 6832, "225": 6804, "210": 6773, "190": 6736}, "Echo_of_Eonar_Waist_HC": {"235": 6832, "225": 6796, "210": 6760, "190": 6692}, "Shadowflame_Prism_Conduit_Hands_HC": {"235": 6831, "225": 6799, "210": 6763, "190": 6709}, "Shadowflame_Prism_Conduit_Head_HM": {"235": 6830, "225": 6786, "210": 6729, "190": 6665}, "Judgment_of_the_Arbiter_Wrists_HM": {"235": 6828, "225": 6800, "210": 6772, "190": 6733}, "Judgment_of_the_Arbiter_Hands_HC": {"235": 6826, "225": 6793, "210": 6757, "190": 6703}, "Echo_of_Eonar_Wrists_HC": {"235": 6825, "225": 6798, "210": 6768, "190": 6730}, "Judgment_of_the_Arbiter_Wrists_HC": {"235": 6823, "225": 6796, "210": 6766, "190": 6730}, "Shadowflame_Prism_Conduit_Head_HC": {"235": 6812, "225": 6770, "210": 6716, "190": 6653}, "Echo_of_Eonar_Finger_HM": {"235": 6805, "225": 6778, "210": 6735, "190": 6676}, "Judgment_of_the_Arbiter_Finger_HM": {"235": 6800, "225": 6773, "210": 6734, "190": 6672}, "Echo_of_Eonar_Finger_HC": {"235": 6787, "225": 6762, "210": 6720, "190": 6663}, "Judgment_of_the_Arbiter_Finger_HC": {"235": 6785, "225": 6760, "210": 6719, "190": 6662}, "Painbreaker_Psalm_Chest_HM": {"235": 6765, "225": 6721, "210": 6662, "190": 6591}, "Painbreaker_Psalm_Back_HM": {"235": 6763, "225": 6741, "210": 6704, "190": 6672}, "Painbreaker_Psalm_Back_HC": {"235": 6756, "225": 6733, "210": 6698, "190": 6666}, "Painbreaker_Psalm_Chest_HC": {"235": 6755, "225": 6713, "210": 6656, "190": 6585}, "Twins_of_the_Sun_Priestess_Conduit_7_Head_HM": {"235": 6753, "225": 6715, "210": 6657, "190": 6593}, "Twins_of_the_Sun_Priestess_Conduit_7_Shoulder_HM": {"235": 6742, "225": 6711, "210": 6672, "190": 6606}, "Twins_of_the_Sun_Priestess_Conduit_7_Head_HC": {"235": 6738, "225": 6699, "210": 6642, "190": 6580}, "Twins_of_the_Sun_Priestess_Conduit_7_Shoulder_HC": {"235": 6734, "225": 6706, "210": 6664, "190": 6601}, "Third_Eye_of_the_Jailer_Waist_HM": {"235": 6732, "225": 6696, "210": 6662, "190": 6591}, "Sephuzs_Proclamation_Chest_HM": {"235": 6731, "225": 6679, "210": 6620, "190": 6550}, "Sephuzs_Proclamation_Shoulder_HM": {"235": 6728, "225": 6701, "210": 6658, "190": 6590}, "Third_Eye_of_the_Jailer_Waist_HC": {"235": 6726, "225": 6690, "210": 6656, "190": 6588}, "Sephuzs_Proclamation_Shoulder_HC": {"235": 6722, "225": 6693, "210": 6653, "190": 6584}, "Sephuzs_Proclamation_Chest_HC": {"235": 6720, "225": 6671, "210": 6612, "190": 6544}, "Third_Eye_of_the_Jailer_Head_HM": {"235": 6719, "225": 6679, "210": 6622, "190": 6560}, "Third_Eye_of_the_Jailer_Shoulder_HM": {"235": 6708, "225": 6678, "210": 6637, "190": 6567}, "Third_Eye_of_the_Jailer_Head_HC": {"235": 6702, "225": 6664, "210": 6610, "190": 6547}, "Third_Eye_of_the_Jailer_Shoulder_HC": {"235": 6700, "225": 6671, "210": 6631, "190": 6562}, "Sephuzs_Proclamation_Neck_HM": {"235": 6593, "225": 6593, "210": 6593, "190": 6595}, "Sephuzs_Proclamation_Neck_HC": {"235": 6576, "225": 6575, "210": 6575, "190": 6575}, "Base": {"DPS": 6691}}, "ids": {"Shadowflame_Prism_Mindbender_Hands_HM": 336143, "Shadowflame_Prism_Mindbender_Head_HM": 336143, "Shadowflame_Prism_Mindbender_Conduit_Hands_HM": 336143, "Shadowflame_Prism_Mindbender_Hands_HC": 336143, "Shadowflame_Prism_Mindbender_Conduit_Head_HM": 336143, "Shadowflame_Prism_Mindbender_Conduit_Hands_HC": 336143, "Shadowflame_Prism_Mindbender_Head_HC": 336143, "Shadowflame_Prism_Mindbender_Conduit_Head_HC": 336143, "Talbadars_Stratagem_Waist_HM": 342415, "Talbadars_Stratagem_Waist_HC": 342415, "Talbadars_Stratagem_Legs_HM": 342415, "Talbadars_Stratagem_Legs_HC": 342415, "Talbadars_Stratagem_Conduit_Waist_HM": 342415, "Talbadars_Stratagem_Conduit_Legs_HM": 342415, "Talbadars_Stratagem_Conduit_Waist_HC": 342415, "Talbadars_Stratagem_Conduit_Legs_HC": 342415, "Eternal_Call_to_the_Void_Hands_HM": 336214, "Eternal_Call_to_the_Void_Wrists_HM": 336214, "Eternal_Call_to_the_Void_Hands_HC": 336214, "Eternal_Call_to_the_Void_Wrists_HC": 336214, "Shadowflame_Prism_Hands_HM": 336143, "Shadowflame_Prism_Hands_HC": 336143, "Shadowflame_Prism_Head_HM": 336143, "Shadowflame_Prism_Head_HC": 336143, "Echo_of_Eonar_Waist_HM": 338477, "Shadowflame_Prism_Conduit_Hands_HM": 336143, "Judgment_of_the_Arbiter_Hands_HM": 339344, "Echo_of_Eonar_Wrists_HM": 338477, "Echo_of_Eonar_Waist_HC": 338477, "Shadowflame_Prism_Conduit_Hands_HC": 336143, "Shadowflame_Prism_Conduit_Head_HM": 336143, "Judgment_of_the_Arbiter_Wrists_HM": 339344, "Judgment_of_the_Arbiter_Hands_HC": 339344, "Echo_of_Eonar_Wrists_HC": 338477, "Judgment_of_the_Arbiter_Wrists_HC": 339344, "Shadowflame_Prism_Conduit_Head_HC": 336143, "Echo_of_Eonar_Finger_HM": 338477, "Judgment_of_the_Arbiter_Finger_HM": 339344, "Echo_of_Eonar_Finger_HC": 338477, "Judgment_of_the_Arbiter_Finger_HC": 339344, "Painbreaker_Psalm_Chest_HM": 336165, "Painbreaker_Psalm_Back_HM": 336165, "Painbreaker_Psalm_Back_HC": 336165, "Painbreaker_Psalm_Chest_HC": 336165, "Twins_of_the_Sun_Priestess_Conduit_7_Head_HM": 336897, "Twins_of_the_Sun_Priestess_Conduit_7_Shoulder_HM": 336897, "Twins_of_the_Sun_Priestess_Conduit_7_Head_HC": 336897, "Twins_of_the_Sun_Priestess_Conduit_7_Shoulder_HC": 336897, "Third_Eye_of_the_Jailer_Waist_HM": 339058, "Sephuzs_Proclamation_Chest_HM": 339348, "Sephuzs_Proclamation_Shoulder_HM": 339348, "Third_Eye_of_the_Jailer_Waist_HC": 339058, "Sephuzs_Proclamation_Shoulder_HC": 339348, "Sephuzs_Proclamation_Chest_HC": 339348, "Third_Eye_of_the_Jailer_Head_HM": 339058, "Third_Eye_of_the_Jailer_Shoulder_HM": 339058, "Third_Eye_of_the_Jailer_Head_HC": 339058, "Third_Eye_of_the_Jailer_Shoulder_HC": 339058, "Sephuzs_Proclamation_Neck_HM": 339348, "Sephuzs_Proclamation_Neck_HC": 339348}, "simulated_steps": [235, 225, 210, 190], "sorted_data_keys": ["Shadowflame_Prism_Mindbender_Hands_HM", "Shadowflame_Prism_Mindbender_Head_HM", "Shadowflame_Prism_Mindbender_Conduit_Hands_HM", "Shadowflame_Prism_Mindbender_Hands_HC", "Shadowflame_Prism_Mindbender_Conduit_Head_HM", "Shadowflame_Prism_Mindbender_Conduit_Hands_HC", "Shadowflame_Prism_Mindbender_Head_HC", "Shadowflame_Prism_Mindbender_Conduit_Head_HC", "Talbadars_Stratagem_Waist_HM", "Talbadars_Stratagem_Waist_HC", "Talbadars_Stratagem_Legs_HM", "Talbadars_Stratagem_Legs_HC", "Talbadars_Stratagem_Conduit_Waist_HM", "Talbadars_Stratagem_Conduit_Legs_HM", "Talbadars_Stratagem_Conduit_Waist_HC", "Talbadars_Stratagem_Conduit_Legs_HC", "Eternal_Call_to_the_Void_Hands_HM", "Eternal_Call_to_the_Void_Wrists_HM", "Eternal_Call_to_the_Void_Hands_HC", "Eternal_Call_to_the_Void_Wrists_HC", "Shadowflame_Prism_Hands_HM", "Shadowflame_Prism_Hands_HC", "Shadowflame_Prism_Head_HM", "Shadowflame_Prism_Head_HC", "Echo_of_Eonar_Waist_HM", "Shadowflame_Prism_Conduit_Hands_HM", "Judgment_of_the_Arbiter_Hands_HM", "Echo_of_Eonar_Wrists_HM", "Echo_of_Eonar_Waist_HC", "Shadowflame_Prism_Conduit_Hands_HC", "Shadowflame_Prism_Conduit_Head_HM", "Judgment_of_the_Arbiter_Wrists_HM", "Judgment_of_the_Arbiter_Hands_HC", "Echo_of_Eonar_Wrists_HC", "Judgment_of_the_Arbiter_Wrists_HC", "Shadowflame_Prism_Conduit_Head_HC", "Echo_of_Eonar_Finger_HM", "Judgment_of_the_Arbiter_Finger_HM", "Echo_of_Eonar_Finger_HC", "Judgment_of_the_Arbiter_Finger_HC", "Painbreaker_Psalm_Chest_HM", "Painbreaker_Psalm_Back_HM", "Painbreaker_Psalm_Back_HC", "Painbreaker_Psalm_Chest_HC", "Twins_of_the_Sun_Priestess_Conduit_7_Head_HM", "Twins_of_the_Sun_Priestess_Conduit_7_Shoulder_HM", "Twins_of_the_Sun_Priestess_Conduit_7_Head_HC", "Twins_of_the_Sun_Priestess_Conduit_7_Shoulder_HC", "Third_Eye_of_the_Jailer_Waist_HM", "Sephuzs_Proclamation_Chest_HM", "Sephuzs_Proclamation_Shoulder_HM", "Third_Eye_of_the_Jailer_Waist_HC", "Sephuzs_Proclamation_Shoulder_HC", "Sephuzs_Proclamation_Chest_HC", "Third_Eye_of_the_Jailer_Head_HM", "Third_Eye_of_the_Jailer_Shoulder_HM", "Third_Eye_of_the_Jailer_Head_HC", "Third_Eye_of_the_Jailer_Shoulder_HC", "Sephuzs_Proclamation_Neck_HM", "Sephuzs_Proclamation_Neck_HC"], "last_updated": "2021-03-11"}