{"name": "Dungeons - hv-sc", "data": {"Kyrian_Pelagos": {"DPS": 5852}, "Necrolord_Marileth_Mastery_PPS": {"DPS": 5813}, "Venthyr_Nadjia": {"DPS": 5799}, "Necrolord_Bonesmith": {"DPS": 5769}, "Necrolord_Marileth_Mastery": {"DPS": 5765}, "Venthyr_Theotar": {"DPS": 5748}, "Night_Fae_Korayn": {"DPS": 5729}, "Necrolord_Emeni": {"DPS": 5713}, "Kyrian_Forgelite": {"DPS": 5692}, "Night_Fae_Dreamweaver": {"DPS": 5683}, "Night_Fae_Dreamweaver_SB": {"DPS": 5681}, "Necrolord_Bonesmith_SS": {"DPS": 5646}, "Venthyr_Draven": {"DPS": 5642}, "Kyrian_Kleia": {"DPS": 5614}, "Night_Fae_Niya": {"DPS": 5594}, "Venthyr_Covenant_Only": {"DPS": 5512}, "Kyrian_Covenant_Only": {"DPS": 5489}, "Necrolord_Covenant_Only": {"DPS": 5475}, "Night_Fae_Covenant_Only": {"DPS": 5455}, "Base": {"DPS": 5353}}, "ids": {"Kyrian_Pelagos": 325013, "Necrolord_Marileth_Mastery_PPS": 323090, "Venthyr_Nadjia": 323673, "Necrolord_Bonesmith": 324724, "Necrolord_Marileth_Mastery": 323074, "Venthyr_Theotar": 323673, "Night_Fae_Korayn": 327661, "Necrolord_Emeni": 324724, "Kyrian_Forgelite": 325013, "Night_Fae_Dreamweaver": 327661, "Night_Fae_Dreamweaver_SB": 319210, "Necrolord_Bonesmith_SS": 326504, "Venthyr_Draven": 323673, "Kyrian_Kleia": 325013, "Night_Fae_Niya": 327661, "Venthyr_Covenant_Only": 323673, "Kyrian_Covenant_Only": 325013, "Necrolord_Covenant_Only": 324724, "Night_Fae_Covenant_Only": 327661}, "simulated_steps": ["DPS"], "sorted_data_keys": ["Kyrian_Pelagos", "Necrolord_Marileth_Mastery_PPS", "Venthyr_Nadjia", "Necrolord_Bonesmith", "Necrolord_Marileth_Mastery", "Venthyr_Theotar", "Night_Fae_Korayn", "Necrolord_Emeni", "Kyrian_Forgelite", "Night_Fae_Dreamweaver", "Night_Fae_Dreamweaver_SB", "Necrolord_Bonesmith_SS", "Venthyr_Draven", "Kyrian_Kleia", "Night_Fae_Niya", "Venthyr_Covenant_Only", "Kyrian_Covenant_Only", "Necrolord_Covenant_Only", "Night_Fae_Covenant_Only"], "last_updated": "2020-11-22"}