{"name": "Dungeons - am - necrolord", "data": {"Marileth-VS_Mastery_PPS": {"DPS": 6736}, "Marileth-VS_Mastery-MD": {"DPS": 6672}, "Marileth-VS_Intellect_PPS": {"DPS": 6422}, "Marileth-VS_Crit_PPS": {"DPS": 6405}, "Marileth-VS_Intellect-MD": {"DPS": 6356}, "Marileth-VS_Crit-MD": {"DPS": 6335}, "Emeni-MD_HA": {"DPS": 6332}, "Emeni-GC-MD": {"DPS": 6307}, "Marileth-PPS": {"DPS": 6303}, "Marileth-MD": {"DPS": 6236}, "Base": {"DPS": 6139}}, "ids": {"Marileth-VS_Mastery_PPS": null, "Marileth-VS_Mastery-MD": null, "Marileth-VS_Intellect_PPS": null, "Marileth-VS_Crit_PPS": null, "Marileth-VS_Intellect-MD": null, "Marileth-VS_Crit-MD": null, "Emeni-MD_HA": null, "Emeni-GC-MD": null, "Marileth-PPS": null, "Marileth-MD": null}, "simulated_steps": ["DPS"], "sorted_data_keys": ["Marileth-VS_Mastery_PPS", "Marileth-VS_Mastery-MD", "Marileth-VS_Intellect_PPS", "Marileth-VS_Crit_PPS", "Marileth-VS_Intellect-MD", "Marileth-VS_Crit-MD", "Emeni-MD_HA", "Emeni-GC-MD", "Marileth-PPS", "Marileth-MD"], "last_updated": "2020-10-20"}