{"name": "Single - hv-sc - venthyr", "data": {"Dissonant_Echoes": {"226": 5668, "213": 5661, "200": 5655, "184": 5645, "171": 5637, "158": 5631, "145": 5623}, "Haunting_Apparitions": {"226": 5561, "213": 5552, "200": 5518, "184": 5533, "171": 5526, "158": 5516, "145": 5507}, "Mind_Devourer": {"226": 5538, "213": 5535, "200": 5531, "184": 5531, "171": 5526, "158": 5524, "145": 5521}, "Rabid_Shadows": {"226": 5479, "213": 5480, "200": 5473, "184": 5473, "171": 5461, "158": 5462, "145": 5443}, "Shattered_Perceptions": {"226": 5475, "213": 5470, "200": 5468, "184": 5465, "171": 5461, "158": 5457, "145": 5453}, "Base": {"DPS": 5418}}, "ids": {"Dissonant_Echoes": 338342, "Haunting_Apparitions": 338319, "Mind_Devourer": 338332, "Rabid_Shadows": 338338, "Shattered_Perceptions": 338315}, "simulated_steps": [226, 213, 200, 184, 171, 158, 145], "sorted_data_keys": ["Dissonant_Echoes", "Haunting_Apparitions", "Mind_Devourer", "Rabid_Shadows", "Shattered_Perceptions"], "last_updated": "2020-12-04"}