{"name": "Composite - stm - kyrian", "data": {"Sinful_Gladiators_Badge_of_Ferocity": {"226": 5286, "220": 5260, "213": 5233, "207": 5208, "200": 5183, "190": 5150}, "Cabalists_Hymnal_Allies_4": {"233": 5187, "220": 5145, "207": 5109, "194": 5074}, "Cabalists_Hymnal_Allies_3": {"233": 5181, "220": 5138, "207": 5103, "194": 5069}, "Cabalists_Hymnal_Allies_2": {"233": 5174, "220": 5132, "207": 5096, "194": 5063}, "Dreadfire_Vessel": {"233": 5170, "220": 5110, "207": 5062, "194": 5019}, "Empyreal_Ordnance": {"226": 5169, "223": 5159, "220": 5151, "216": 5138, "213": 5129, "210": 5119, "207": 5111, "204": 5103, "203": 5102, "200": 5093, "197": 5083, "194": 5076, "190": 5066, "187": 5058, "183": 5049, "170": 5019, "158": 4992}, "Inscrutable_Quantum_Device": {"226": 5166, "223": 5156, "220": 5149, "216": 5141, "213": 5132, "210": 5124, "207": 5115, "204": 5107, "203": 5107, "200": 5098, "197": 5091, "194": 5083, "190": 5071, "187": 5066, "183": 5058, "170": 5027, "158": 5001}, "Cabalists_Hymnal_Allies_1": {"233": 5166, "220": 5125, "207": 5089, "194": 5058}, "Soulletting_Ruby": {"226": 5163, "223": 5151, "220": 5144, "216": 5136, "213": 5126, "210": 5119, "207": 5109, "204": 5101, "203": 5100, "200": 5092, "197": 5084, "194": 5075, "190": 5066, "187": 5057, "183": 5051, "170": 5020, "158": 4996}, "Cabalists_Hymnal_Allies_0": {"233": 5158, "220": 5117, "207": 5083, "194": 5052}, "Glyph_of_Assimilation": {"226": 5152, "213": 5101, "200": 5052, "187": 5010}, "Soul_Igniter": {"226": 5150, "213": 5097, "200": 5050, "187": 5008}, "Macabre_Sheet_Music": {"226": 5137, "213": 5103, "200": 5073, "187": 5042}, "Satchel_of_Misbegotten_Minions": {"226": 5118, "223": 5107, "220": 5094, "216": 5083, "213": 5072, "210": 5064, "207": 5049, "204": 5039, "203": 5039, "200": 5030, "197": 5021, "194": 5010, "190": 4999, "187": 4992, "183": 4985, "170": 4964, "158": 4948}, "Sinful_Aspirants_Badge_of_Ferocity": {"190": 5118, "184": 5101, "177": 5081, "171": 5065, "164": 5047, "158": 5032}, "Sinful_Gladiators_Insignia_of_Alacrity": {"226": 5108, "220": 5090, "213": 5075, "207": 5060, "200": 5047, "190": 5024}, "Infinitely_Divisible_Ooze": {"226": 5089, "223": 5078, "220": 5068, "216": 5059, "213": 5049, "210": 5039, "207": 5028, "204": 5018, "203": 5019, "200": 5010, "197": 5001, "194": 4992, "190": 4982, "187": 4976, "183": 4969, "170": 4949, "158": 4934}, "Sunblood_Amethyst": {"226": 5055, "223": 5049, "220": 5039, "216": 5031, "213": 5024, "210": 5019, "207": 5009, "204": 5005, "203": 5004, "200": 4999, "197": 4991, "194": 4984, "190": 4976, "187": 4971, "183": 4966, "170": 4947, "158": 4934}, "Sinful_Aspirants_Insignia_of_Alacrity": {"190": 5034, "184": 5021, "177": 5007, "171": 4996, "164": 4982, "158": 4972}, "Overflowing_Anima_Prison": {"226": 5034, "223": 5025, "220": 5019, "216": 5014, "213": 5007, "210": 5000, "207": 4994, "204": 4986, "203": 4986, "200": 4981, "197": 4974, "194": 4968, "190": 4961, "187": 4956, "183": 4952, "170": 4929, "158": 4913}, "Darkmoon_Deck_Putrescence": {"200": 5005}, "Unbound_Changeling": {"226": 4996, "223": 4989, "220": 4983, "216": 4978, "213": 4971, "210": 4965, "207": 4958, "204": 4953, "203": 4952, "200": 4948, "197": 4942, "194": 4936, "190": 4929, "187": 4926, "183": 4921, "170": 4902, "158": 4888}, "Spiritual_Alchemy_Stone": {"165": 4969}, "Vial_of_Caustic_Liquid": {"155": 4961}, "Withergrove_Shardling": {"155": 4953}, "Flame_of_Battle": {"155": 4884}, "Base": {"DPS": 4767}}, "ids": {"Sinful_Gladiators_Badge_of_Ferocity": 175921, "Cabalists_Hymnal_Allies_4": 184028, "Cabalists_Hymnal_Allies_3": 184028, "Cabalists_Hymnal_Allies_2": 184028, "Dreadfire_Vessel": 184030, "Empyreal_Ordnance": 180117, "Inscrutable_Quantum_Device": 179350, "Cabalists_Hymnal_Allies_1": 184028, "Soulletting_Ruby": 178809, "Cabalists_Hymnal_Allies_0": 184028, "Glyph_of_Assimilation": 184021, "Soul_Igniter": 184019, "Macabre_Sheet_Music": 184024, "Satchel_of_Misbegotten_Minions": 178772, "Sinful_Aspirants_Badge_of_Ferocity": 175884, "Sinful_Gladiators_Insignia_of_Alacrity": 178386, "Infinitely_Divisible_Ooze": 178769, "Sunblood_Amethyst": 178826, "Sinful_Aspirants_Insignia_of_Alacrity": 178298, "Overflowing_Anima_Prison": 178849, "Darkmoon_Deck_Putrescence": 173069, "Unbound_Changeling": 178708, "Spiritual_Alchemy_Stone": 171323, "Vial_of_Caustic_Liquid": 181503, "Withergrove_Shardling": 181459, "Flame_of_Battle": 181501}, "simulated_steps": [233, 226, 223, 220, 216, 213, 210, 207, 204, 203, 200, 197, 195, 194, 190, 187, 184, 183, 177, 175, 171, 170, 165, 164, 158, 155], "sorted_data_keys": ["Sinful_Gladiators_Badge_of_Ferocity", "Cabalists_Hymnal_Allies_4", "Cabalists_Hymnal_Allies_3", "Cabalists_Hymnal_Allies_2", "Dreadfire_Vessel", "Empyreal_Ordnance", "Inscrutable_Quantum_Device", "Cabalists_Hymnal_Allies_1", "Soulletting_Ruby", "Cabalists_Hymnal_Allies_0", "Glyph_of_Assimilation", "Soul_Igniter", "Macabre_Sheet_Music", "Satchel_of_Misbegotten_Minions", "Sinful_Aspirants_Badge_of_Ferocity", "Sinful_Gladiators_Insignia_of_Alacrity", "Infinitely_Divisible_Ooze", "Sunblood_Amethyst", "Sinful_Aspirants_Insignia_of_Alacrity", "Overflowing_Anima_Prison", "Darkmoon_Deck_Putrescence", "Unbound_Changeling", "Spiritual_Alchemy_Stone", "Vial_of_Caustic_Liquid", "Withergrove_Shardling", "Flame_of_Battle"], "last_updated": "2020-11-14"}