{"name": "Dungeons - stm - night_fae", "data": {"Empyreal_Ordnance": {"226": 5164, "223": 5160, "220": 5164, "216": 5160, "213": 5158, "210": 5157, "207": 5155, "204": 5154, "203": 5155, "200": 5151, "197": 5148, "194": 5146, "190": 5148, "187": 5141, "183": 5143, "170": 5136}, "Infinitely_Divisible_Ooze": {"226": 5311, "223": 5302, "220": 5297, "216": 5295, "213": 5285, "210": 5277, "207": 5271, "204": 5269, "203": 5268, "200": 5259, "197": 5255, "194": 5247, "190": 5240, "187": 5237, "183": 5231, "170": 5215, "158": 5196}, "Inscrutable_Quantum_Device": {"226": 5313, "223": 5306, "220": 5298, "216": 5291, "213": 5285, "210": 5280, "207": 5274, "204": 5267, "203": 5267, "200": 5261, "197": 5253, "194": 5247, "190": 5242, "187": 5239, "183": 5229, "170": 5211, "158": 5194}, "Overflowing_Anima_Prison": {"226": 5333, "223": 5332, "220": 5325, "216": 5314, "213": 5306, "210": 5300, "207": 5296, "204": 5286, "203": 5289, "200": 5278, "197": 5270, "194": 5268, "190": 5260, "187": 5256, "183": 5247, "170": 5226, "158": 5209}, "Satchel_of_Misbegotten_Minions": {"226": 5486, "223": 5481, "220": 5473, "216": 5458, "213": 5452, "210": 5441, "207": 5435, "204": 5424, "203": 5425, "200": 5417, "197": 5407, "194": 5404, "190": 5387, "187": 5382, "183": 5378, "170": 5347, "158": 5324}, "Soulletting_Ruby": {"226": 5310, "223": 5303, "220": 5299, "216": 5291, "213": 5286, "210": 5277, "207": 5276, "204": 5266, "203": 5269, "200": 5261, "197": 5254, "194": 5246, "190": 5239, "187": 5236, "183": 5233, "170": 5213, "158": 5194}, "Sunblood_Amethyst": {"226": 5393, "223": 5387, "220": 5381, "216": 5372, "213": 5363, "210": 5359, "207": 5353, "204": 5345, "203": 5343, "200": 5337, "197": 5333, "194": 5325, "190": 5318, "187": 5310, "183": 5308, "170": 5290, "158": 5273}, "Unbound_Changeling": {"226": 5312, "223": 5307, "220": 5296, "216": 5292, "213": 5286, "210": 5280, "207": 5274, "204": 5267, "203": 5266, "200": 5261, "197": 5256, "194": 5247, "190": 5243, "187": 5235, "183": 5230, "170": 5212, "158": 5197}, "Darkmoon_Deck_Putrescence": {"200": 5299}, "Flame_of_Battle": {"155": 5248}, "Sinful_Aspirants_Badge_of_Ferocity": {"175": 5325}, "Sinful_Aspirants_Insignia_of_Alacrity": {"175": 5325}, "Sinful_Gladiators_Badge_of_Ferocity": {"195": 5485}, "Sinful_Gladiators_Insignia_of_Alacrity": {"195": 5419}, "Spiritual_Alchemy_Stone": {"165": 5287}, "Vial_of_Caustic_Liquid": {"155": 5265}, "Withergrove_Shardling": {"155": 5276}, "Cabalists_Hymnal_Allies_0": {"233": 5432, "220": 5390, "207": 5361, "194": 5332}, "Cabalists_Hymnal_Allies_1": {"233": 5440, "220": 5402, "207": 5373, "194": 5337}, "Cabalists_Hymnal_Allies_2": {"233": 5452, "220": 5412, "207": 5381, "194": 5345}, "Cabalists_Hymnal_Allies_3": {"233": 5460, "220": 5420, "207": 5389, "194": 5353}, "Cabalists_Hymnal_Allies_4": {"233": 5469, "220": 5431, "207": 5396, "194": 5359}, "Dreadfire_Vessel": {"233": 5465, "220": 5406, "207": 5363, "194": 5320}, "Glyph_of_Assimilation": {"226": 5446, "213": 5400, "200": 5360, "187": 5318}, "Macabre_Sheet_Music": {"226": 5521, "213": 5479, "200": 5434, "187": 5396}, "Soul_Igniter": {"226": 5085, "213": 5060, "200": 5039, "187": 5015}, "Base": {"DPS": 5067}}, "ids": {"Empyreal_Ordnance": 180117, "Infinitely_Divisible_Ooze": 178769, "Inscrutable_Quantum_Device": 179350, "Overflowing_Anima_Prison": 178849, "Satchel_of_Misbegotten_Minions": 178772, "Soulletting_Ruby": 178809, "Sunblood_Amethyst": 178826, "Unbound_Changeling": 178708, "Darkmoon_Deck_Putrescence": 173069, "Flame_of_Battle": 181501, "Sinful_Aspirants_Badge_of_Ferocity": 175884, "Sinful_Aspirants_Insignia_of_Alacrity": 178298, "Sinful_Gladiators_Badge_of_Ferocity": 175921, "Sinful_Gladiators_Insignia_of_Alacrity": 178386, "Spiritual_Alchemy_Stone": 171323, "Vial_of_Caustic_Liquid": 181503, "Withergrove_Shardling": 181459, "Cabalists_Hymnal_Allies_0": 184028, "Cabalists_Hymnal_Allies_1": 184028, "Cabalists_Hymnal_Allies_2": 184028, "Cabalists_Hymnal_Allies_3": 184028, "Cabalists_Hymnal_Allies_4": 184028, "Dreadfire_Vessel": 184030, "Glyph_of_Assimilation": 184021, "Macabre_Sheet_Music": 184024, "Soul_Igniter": 184019}, "simulated_steps": [233, 226, 223, 220, 216, 213, 210, 207, 204, 203, 200, 197, 195, 194, 190, 187, 183, 175, 170, 165, 158, 155], "sorted_data_keys": ["Empyreal_Ordnance", "Infinitely_Divisible_Ooze", "Inscrutable_Quantum_Device", "Overflowing_Anima_Prison", "Satchel_of_Misbegotten_Minions", "Soulletting_Ruby", "Sunblood_Amethyst", "Unbound_Changeling", "Darkmoon_Deck_Putrescence", "Flame_of_Battle", "Sinful_Aspirants_Badge_of_Ferocity", "Sinful_Aspirants_Insignia_of_Alacrity", "Sinful_Gladiators_Badge_of_Ferocity", "Sinful_Gladiators_Insignia_of_Alacrity", "Spiritual_Alchemy_Stone", "Vial_of_Caustic_Liquid", "Withergrove_Shardling", "Cabalists_Hymnal_Allies_0", "Cabalists_Hymnal_Allies_1", "Cabalists_Hymnal_Allies_2", "Cabalists_Hymnal_Allies_3", "Cabalists_Hymnal_Allies_4", "Dreadfire_Vessel", "Glyph_of_Assimilation", "Macabre_Sheet_Music", "Soul_Igniter"], "last_updated": "2020-10-05"}